powerpoint/__init__.py
powerpoint/chart_manager.py
powerpoint/presentation_manager.py
powerpoint/server.py
powerpoint/vision_manager.py
powerpoint_mcp_server-0.1.0.dist-info/licenses/LICENSE
powerpoint_mcp_server-0.1.0.dist-info/METADATA
powerpoint_mcp_server-0.1.0.dist-info/WHEEL
powerpoint_mcp_server-0.1.0.dist-info/entry_points.txt
powerpoint_mcp_server-0.1.0.dist-info/top_level.txt
powerpoint_mcp_server-0.1.0.dist-info/RECORD
