Metadata-Version: 2.4
Name: powerpoint-mcp-server
Version: 0.1.0
Summary: Add your description here
Author-email: Russell Ashby <158164671+supercurses@users.noreply.github.com>
Requires-Python: >=3.13
License-File: LICENSE
Requires-Dist: argparse>=1.4.0
Requires-Dist: asyncio>=3.4.3
Requires-Dist: mcp>=1.5.0
Requires-Dist: pillow>=11.1.0
Requires-Dist: python-pptx>=1.0.2
Requires-Dist: requests>=2.32.3
Requires-Dist: together>=1.5.3
Dynamic: license-file
